carneiro_graficos/__init__.py
carneiro_graficos/carneiro_graficos.py
carneiro_graficos-0.2.0.dist-info/METADATA
carneiro_graficos-0.2.0.dist-info/WHEEL
carneiro_graficos-0.2.0.dist-info/top_level.txt
carneiro_graficos-0.2.0.dist-info/RECORD
