Metadata-Version: 2.1
Name: carneiro_graficos
Version: 0.2.0
Summary: Uma simples biblioteca para criar gráficos usando matplotlib
Home-page: https://github.com/antonioanerao/carneiro_graficos
Author: Antonio Anerão
Author-email: anerao.junior@gmail.com
Classifier: Programming Language :: Python :: 3
Classifier: License :: OSI Approved :: MIT License
Classifier: Operating System :: OS Independent
Requires-Python: >=3.6
Requires-Dist: matplotlib
Requires-Dist: numpy
